mork/__init__.py
mork/virtualenv.py
mork-0.1.4.dist-info/METADATA
mork-0.1.4.dist-info/RECORD
mork-0.1.4.dist-info/WHEEL
mork-0.1.4.dist-info/top_level.txt
mork-0.1.4.dist-info/zip-safe
