Metadata-Version: 2.1
Name: mork
Version: 0.1.4
Summary: A project for installing packages across the virtualenv boundary.
Home-page: https://github.com/sarugaku/mork
Author: Dan Ryan
Author-email: dan@danryan.co
License: ISC License
Keywords: package management,package installer,virtual environment,pipenv,requirementslib,pipfile,dependencies,dependency management
Platform: UNKNOWN
Classifier: Development Status :: 1 - Planning
Classifier: License :: OSI Approved :: ISC License (ISCL)
Classifier: Operating System :: OS Independent
Classifier: Programming Language :: Python :: 2
Classifier: Programming Language :: Python :: 2.6
Classifier: Programming Language :: Python :: 2.7
Classifier: Programming Language :: Python :: 3
Classifier: Programming Language :: Python :: 3.4
Classifier: Programming Language :: Python :: 3.5
Classifier: Programming Language :: Python :: 3.6
Classifier: Programming Language :: Python :: 3.7
Classifier: Topic :: Software Development :: Libraries :: Python Modules
Requires-Python: >=2.6,!=3.0,!=3.1,!=3.2,!=3.3
Provides-Extra: tests
Requires-Dist: cached-property
Requires-Dist: distlib
Requires-Dist: packagebuilder
Requires-Dist: pip-shims
Requires-Dist: recursive-monkey-patch
Requires-Dist: requirementslib
Requires-Dist: setuptools
Requires-Dist: six
Requires-Dist: virtualenv
Requires-Dist: vistir[spinner]
Provides-Extra: tests
Requires-Dist: pytest-timeout; extra == 'tests'
Requires-Dist: pytest-xdist; extra == 'tests'
Requires-Dist: pytest-cov; extra == 'tests'
Requires-Dist: pytest; extra == 'tests'
